deper-0.0.8.dist-info/DESCRIPTION.rst
deper-0.0.8.dist-info/METADATA
deper-0.0.8.dist-info/RECORD
deper-0.0.8.dist-info/WHEEL
deper-0.0.8.dist-info/metadata.json
deper-0.0.8.dist-info/top_level.txt
deper-0.0.8.dist-info/zip-safe
deploy/__init__.py
deploy/deploy.py
