Metadata-Version: 2.0
Name: deper
Version: 0.0.8
Summary: 项目部署工具
Home-page: https://github.com/toalaska/deploy
Author: toalaska
Author-email: toalaska@126.com
License: BSD
Download-URL: https://github.com/toalaska/deploy/archive/master.zip
Keywords: deploy,oss,ssh
Platform: UNKNOWN
Requires-Dist: requests
